container_workflow_tool/__init__.py
container_workflow_tool/cli.py
container_workflow_tool/cli_common.py
container_workflow_tool/config.py
container_workflow_tool/constants.py
container_workflow_tool/distgit.py
container_workflow_tool/dockerfile.py
container_workflow_tool/git_operations.py
container_workflow_tool/koji.py
container_workflow_tool/main.py
container_workflow_tool/sync.py
container_workflow_tool/utility.py
container_workflow_tool/config/default.yaml
container_workflow_tool/config/f27.yaml
container_workflow_tool/config/f28.yaml
container_workflow_tool/config/f29.yaml
container_workflow_tool/config/f30.yaml
container_workflow_tool/config/f31.yaml
container_workflow_tool/config/f32.yaml
container_workflow_tool/config/f33.yaml
container_workflow_tool/config/f34.yaml
container_workflow_tool/config/rawhide.yaml
container_workflow_tool/config/share/cwt_config.yaml
container_workflow_tool/config/share/urls.yaml
container_workflow_tool-1.5.10.dist-info/LICENSE
container_workflow_tool-1.5.10.dist-info/METADATA
container_workflow_tool-1.5.10.dist-info/WHEEL
container_workflow_tool-1.5.10.dist-info/entry_points.txt
container_workflow_tool-1.5.10.dist-info/top_level.txt
container_workflow_tool-1.5.10.dist-info/zip-safe
container_workflow_tool-1.5.10.dist-info/RECORD
